[
{
	"id":33,
	"url":"img/f2_1.jpg",
	"name":"baby同款墨镜女潮大框超轻太阳镜明星太阳眼镜偏...",
	"del":"106.8",
	"price":"89.0"
},
{
	"id":34,
	"url":"img/f2_2.jpg",
	"name":"2016新款蛤蟆镜经典太阳镜女潮偏光镜彩膜个性情...",
	"del":"106.8",
	"price":"89.0"
},
{
	"id":35,
	"url":"img/f2_3.jpg",
	"name":"2016新款偏光大框太阳眼镜女潮圆脸女士墨镜防紫...",
	"del":"165.6",
	"price":"138.0"
},
{
	"id":36,
	"url":"img/f2_4.jpg",
	"name":"2016新款墨镜女潮偏光太阳镜女个性明星款圆形眼...",
	"del":"117.6",
	"price":"98.0"
},
{
	"id":37,
	"url":"img/f2_5.jpg",
	"name":"2016个性潮人圆脸墨镜长脸男复古眼镜大框方形太...",
	"del":"117.6",
	"price":"98.0"
},
{
	"id":38,
	"url":"img/f2_6.jpg",
	"name":"新款大框男士太阳眼镜女潮蛤蟆镜圆脸偏光墨镜防紫外...",
	"del":"117.6",
	"price":"98.0"
},
{
	"id":39,
	"url":"img/f2_7.jpg",
	"name":"新款大框男士太阳镜男开车蛤蟆镜女士圆脸偏光镜司机...",
	"del":"117.6",
	"price":"98.0"
},
{
	"id":40,
	"url":"img/f2_8.jpg",
	"name":"新款潮韩版墨镜太阳镜明星款半框炫彩女圆形圆脸偏光...",
	"del":"47.8",
	"price":"39.9"
},
{
	"id":41,
	"url":"img/f2_9.jpg",
	"name":"2016春秋季新款韩版胖MM大码女装宽松中长款假...",
	"del":"93.2",
	"price":"78.2"
},
{
	"id":42,
	"url":"img/f2_10.jpg",
	"name":"欧洲站2016春秋女宽松显瘦长袖中长款针织连衣裙...",
	"del":"395.7",
	"price":"328.8"
},
{
	"id":43,
	"url":"img/f2_11.jpg",
	"name":"千与千寻 2016春秋新款 女装蕾丝长裙 复古小...",
	"del":"220.7",
	"price":"186.2"
},
{
	"id":44,
	"url":"img/f2_12.jpg",
	"name":"芭欧 海宁 秋冬新款多色系狐狸毛皮草外套女士修身...",
	"del":"1361.5",
	"price":"1051.3"
},
{
	"id":45,
	"url":"img/f2_13.jpg",
	"name":"高端2015夏装新款修身淑坊女女装蕾丝短袖复女连...",
	"del":"247.8",
	"price":"199.9"
},
{
	"id":46,
	"url":"img/f2_14.jpg",
	"name":"2015新款修身开衫短款七分袖小西装女薄网纱披肩...",
	"del":"347.8",
	"price":"239.9"
},
{
	"id":47,
	"url":"img/f2_15.jpg",
	"name":"夏装新款修身假两件无袖绣花蕾丝连衣裙",
	"del":"348.0",
	"price":"298.0"
},
{
	"id":48,
	"url":"img/f2_16.jpg",
	"name":"2015夏装韩版修身白色小西装女薄外套",
	"del":"478.0",
	"price":"398.0"
}

]
